klv/__init__.py
klv/klv.py
klv-0.0.5.dist-info/LICENSE
klv-0.0.5.dist-info/METADATA
klv-0.0.5.dist-info/WHEEL
klv-0.0.5.dist-info/top_level.txt
klv-0.0.5.dist-info/RECORD
