Metadata-Version: 2.1
Name: klv
Version: 0.0.5
Summary: Key Length Value encoding and decoding
Home-page: https://github.com/mjohnsullivan/python-klv
Author: Arts Alliance Media
Author-email: dev@artsalliancemedia.com
License: MIT
Platform: UNKNOWN
Classifier: Development Status :: 3 - Alpha
Classifier: Intended Audience :: Developers
Classifier: License :: OSI Approved :: MIT License
Classifier: Operating System :: OS Independent
Classifier: Programming Language :: Python
